microns_datacleaner/__init__.py
microns_datacleaner/downloader.py
microns_datacleaner/filters/__init__.py
microns_datacleaner/filters/filters.py
microns_datacleaner/mic_datacleaner.py
microns_datacleaner/processing.py
microns_datacleaner/remapper/__init__.py
microns_datacleaner/remapper/remapper.py
microns_datacleaner/ruff.toml
microns_datacleaner-0.1.5.dist-info/LICENSE.txt
microns_datacleaner-0.1.5.dist-info/METADATA
microns_datacleaner-0.1.5.dist-info/WHEEL
microns_datacleaner-0.1.5.dist-info/RECORD
