Metadata-Version: 2.3
Name: Microns-DataCleaner
Version: 0.1.5
Summary: Provides common functions to download and process data from the mm3 data.
Keywords: neuroscience
Author: Victor Buendia
Author-email: victor.buendia@unibocconi.it
Maintainer: All contributors
Requires-Python: >=3.9
Classifier: Development Status :: 2 - Pre-Alpha
Classifier: Intended Audience :: Science/Research
Classifier: Operating System :: OS Independent
Classifier: Programming Language :: Python :: 3
Requires-Dist: caveclient
Requires-Dist: numpy
Requires-Dist: pandas
Requires-Dist: scipy
Requires-Dist: standard_transform
Requires-Dist: tqdm
